fudstop_middleware/__init__.py
fudstop_middleware/fudstop_channels.py
fudstop_middleware/imps.py
fudstop_middleware-0.1.5.dist-info/METADATA
fudstop_middleware-0.1.5.dist-info/WHEEL
fudstop_middleware-0.1.5.dist-info/top_level.txt
fudstop_middleware-0.1.5.dist-info/RECORD
